pyqmlapp/PluginLoader.py
pyqmlapp/__init__.py
pyqmlapp/main.py
pyqmlapp-0.2.1.dist-info/LICENSE.txt
pyqmlapp-0.2.1.dist-info/METADATA
pyqmlapp-0.2.1.dist-info/WHEEL
pyqmlapp-0.2.1.dist-info/entry_points.txt
pyqmlapp-0.2.1.dist-info/top_level.txt
pyqmlapp-0.2.1.dist-info/RECORD
